README.rst
setup.py
seismograph/__init__.py
seismograph/__main__.py
seismograph/case.py
seismograph/collector.py
seismograph/config.py
seismograph/datastructures.py
seismograph/exceptions.py
seismograph/extensions.py
seismograph/layers.py
seismograph/loader.py
seismograph/program.py
seismograph/reason.py
seismograph/result.py
seismograph/runnable.py
seismograph/scope.py
seismograph/script.py
seismograph/steps.py
seismograph/suite.py
seismograph/tree.py
seismograph/xunit.py
seismograph.egg-info/PKG-INFO
seismograph.egg-info/SOURCES.txt
seismograph.egg-info/dependency_links.txt
seismograph.egg-info/entry_points.txt
seismograph.egg-info/not-zip-safe
seismograph.egg-info/requires.txt
seismograph.egg-info/top_level.txt
seismograph/ext/__init__.py
seismograph/ext/alchemy/__init__.py
seismograph/ext/alchemy/constants.py
seismograph/ext/alchemy/exceptions.py
seismograph/ext/alchemy/extension.py
seismograph/ext/alchemy/install.py
seismograph/ext/alchemy/orm.py
seismograph/ext/alchemy/registry.py
seismograph/ext/alchemy/session.py
seismograph/ext/builder/__init__.py
seismograph/ext/builder/collector.py
seismograph/ext/builder/exceptions.py
seismograph/ext/builder/factory.py
seismograph/ext/builder/rule.py
seismograph/ext/builder/signature.py
seismograph/ext/builder/staging.py
seismograph/ext/mocker/__init__.py
seismograph/ext/mocker/__main__.py
seismograph/ext/mocker/api.py
seismograph/ext/mocker/client.py
seismograph/ext/mocker/constants.py
seismograph/ext/mocker/exceptions.py
seismograph/ext/mocker/extension.py
seismograph/ext/mocker/mocks.py
seismograph/ext/mocker/patch.py
seismograph/ext/mocker/server.py
seismograph/ext/mocker/tools.py
seismograph/ext/mocker/runners/__init__.py
seismograph/ext/mocker/runners/gevent.py
seismograph/ext/mocker/runners/threading.py
seismograph/ext/seisma/__init__.py
seismograph/ext/seisma/layers.py
seismograph/ext/selenium/__init__.py
seismograph/ext/selenium/browser.py
seismograph/ext/selenium/case.py
seismograph/ext/selenium/drivers.py
seismograph/ext/selenium/exceptions.py
seismograph/ext/selenium/extension.py
seismograph/ext/selenium/pageobject.py
seismograph/ext/selenium/polling.py
seismograph/ext/selenium/query.py
seismograph/ext/selenium/router.py
