Metadata-Version: 1.1
Name: seismograph
Version: 0.5.4
Summary: Framework for test development
Home-page: https://github.com/trifonovmixail/seismograph
Author: Mikhail Trifonov
Author-email: trifonovmixail@ya.ru
License: GNU LGPL
Keywords: test unittest framework
Platform: any
Classifier: Development Status :: 4 - Beta
Classifier: Natural Language :: Russian
Classifier: Intended Audience :: Developers
Classifier: Operating System :: OS Independent
Classifier: Programming Language :: Python
Classifier: Programming Language :: Python :: 2.7
Classifier: Programming Language :: Python :: 3
Classifier: Programming Language :: Python :: Implementation :: CPython
Classifier: Topic :: Software Development :: Testing
